Workbook

Sheet Dashboard
A1: ICICI Bank - Retail Loan Underwriting Dashboard
A2: Sample project: 120 synthetic loan applications screened against a simple policy (income, FOIR, credit score, age). Not real bank data.
A4: Applications | C4: Requested (₹ cr) | E4: Approval rate | G4: Avg interest rate | I4: Avg FOIR | K4: Approved (₹ cr)
A5: =Summary!B11 -> 120 | C5: =Summary!C11 -> 14.791 | E5: =Summary!G11 -> 0.66666667 | G5: =Summary!H11 -> 0.10579167 | I5: =Summary!I11 -> 0.29563973 | K5: =Summary!J11 -> 9.344
A40: Quick read (auto-updates):
A41: ="- Highest approval rate: "&INDEX(Summary!A6:A10,MATCH(MAX(Summary!G6:G10),Summary!G6:G10,0))&" ("&TEXT(MAX(Summary!G6:G10),"0%")&"); lowest: "&INDEX(Summary!A6:A10,MATCH(MIN(Summary!G6:G10),Summary!G6:G10,0))&" ("&TEXT(MIN(Summary!G6:G10),"0%")&")." -> - Highest approval rate: Education Loan (100%); lowest: Business Loan (40%).
A42: ="- Most common rejection reason: "&INDEX(Summary!A18:A21,MATCH(MAX(Summary!B18:B21),Summary!B18:B21,0))&" ("&MAX(Summary!B18:B21)&" applications)." -> - Most common rejection reason: Reject - Low Score (20 applications).
A43: ="- Risk-based pricing: avg rate is "&TEXT(Summary!E27,"0.0%")&" for Poor scores vs "&TEXT(Summary!E31,"0.0%")&" for Excellent scores." -> - Risk-based pricing: avg rate is 11.3% for Poor scores vs 9.8% for Excellent scores.
A44: - Change any yellow / blue cell on the Policy sheet (e.g. max FOIR) and every table and chart refreshes.

Sheet Data
A1: App ID | B1: Customer Name | C1: City | D1: Product | E1: Age | F1: Monthly Income (₹) | G1: Credit Score | H1: Loan Amount (₹) | I1: Tenure (yrs) | J1: Existing EMI (₹) | K1: Score Band | L1: Interest Rate | M1: New EMI (₹) | N1: FOIR | O1: Max Eligible Amt (₹) | P1: Decision | R1: Note: columns A-J are sample applicant data (synthetic, randomly generated). Columns K-P are formulas driven by the Policy sheet.
A2: APP1001 | B2: Manish Mehta | C2: Mumbai | D2: Auto Loan | E2: 41 | F2: 29000 | G2: 746 | H2: 290000 | I2: 5 | J2: 3000 | K2: =INDEX(Policy!$B$13:$B$17,MATCH(G2,Policy!$A$13:$A$17,1)) -> Good | L2: =INDEX(Policy!$B$5:$B$9,MATCH(D2,Policy!$A$5:$A$9,0))+INDEX(Policy!$C$13:$C$17,MATCH(G2,Policy!$A$13:$A$17,1)) -> 0.1 | M2: =PMT(L2/12,I2*12,-H2) -> 6161.643 | N2: =(M2+J2)/F2 -> 0.31591872 | O2: =MAX(0,ROUND(PV(L2/12,I2*12,-(INDEX(Policy!$D$5:$D$9,MATCH(D2,Policy!$A$5:$A$9,0))*F2-J2)),-4)) -> 540000 | P2: =IF(G2<INDEX(Policy!$E$5:$E$9,MATCH(D2,Policy!$A$5:$A$9,0)),"Reject - Low Score",IF(E2+I2>Policy!$B$20,"Reject - Age",IF(I2>INDEX(Policy!$C$5:$C$9,MATCH(D2,Policy!$A$5:$A$9,0)),"Reject - Tenure",IF(N2<=INDEX(Policy!$D$5:$D$9,MATCH(D2,Policy!$A$5:$A$9,0)),"Approve",IF(N2<=INDEX(Policy!$D$5:$D$9,MATCH(D2,Policy!$A$5:$A$9,0))+Policy!$B$21,"Refer to Manager","Reject - High FOIR"))))) -> Approve
A3: APP1002 | B3: Pooja Patel | C3: Mumbai | D3: Business Loan | E3: 25 | F3: 100000 | G3: 761 | H3: 710000 | I3: 5 | J3: 0 | K3: =INDEX(Policy!$B$13:$B$17,MATCH(G3,Policy!$A$13:$A$17,1)) -> Very Good | L3: =INDEX(Policy!$B$5:$B$9,MATCH(D3,Policy!$A$5:$A$9,0))+INDEX(Policy!$C$13:$C$17,MATCH(G3,Policy!$A$13:$A$17,1)) -> 0.1225 | M3: =PMT(L3/12,I3*12,-H3) -> 15883.401 | N3: =(M3+J3)/F3 -> 0.15883401 | O3: =MAX(0,ROUND(PV(L3/12,I3*12,-(INDEX(Policy!$D$5:$D$9,MATCH(D3,Policy!$A$5:$A$9,0))*F3-J3)),-4)) -> 2240000 | P3: =IF(G3<INDEX(Policy!$E$5:$E$9,MATCH(D3,Policy!$A$5:$A$9,0)),"Reject - Low Score",IF(E3+I3>Policy!$B$20,"Reject - Age",IF(I3>INDEX(Policy!$C$5:$C$9,MATCH(D3,Policy!$A$5:$A$9,0)),"Reject - Tenure",IF(N3<=INDEX(Policy!$D$5:$D$9,MATCH(D3,Policy!$A$5:$A$9,0)),"Approve",IF(N3<=INDEX(Policy!$D$5:$D$9,MATCH(D3,Policy!$A$5:$A$9,0))+Policy!$B$21,"Refer to Manager","Reject - High FOIR"))))) -> Approve
A4: APP1003 | B4: Swati Mehta | C4: Bengaluru | D4: Home Loan | E4: 44 | F4: 51000 | G4: 754 | H4: 1310000 | I4: 15 | J4: 0 | K4: =INDEX(Policy!$B$13:$B$17,MATCH(G4,Policy!$A$13:$A$17,1)) -> Very Good | L4: =INDEX(Policy!$B$5:$B$9,MATCH(D4,Policy!$A$5:$A$9,0))+INDEX(Policy!$C$13:$C$17,MATCH(G4,Policy!$A$13:$A$17,1)) -> 0.09 | M4: =PMT(L4/12,I4*12,-H4) -> 13286.892 | N4: =(M4+J4)/F4 -> 0.2605273 | O4: =MAX(0,ROUND(PV(L4/12,I4*12,-(INDEX(Policy!$D$5:$D$9,MATCH(D4,Policy!$A$5:$A$9,0))*F4-J4)),-4)) -> 2510000 | P4: =IF(G4<INDEX(Policy!$E$5:$E$9,MATCH(D4,Policy!$A$5:$A$9,0)),"Reject - Low Score",IF(E4+I4>Policy!$B$20,"Reject - Age",IF(I4>INDEX(Policy!$C$5:$C$9,MATCH(D4,Policy!$A$5:$A$9,0)),"Reject - Tenure",IF(N4<=INDEX(Policy!$D$5:$D$9,MATCH(D4,Policy!$A$5:$A$9,0)),"Approve",IF(N4<=INDEX(Policy!$D$5:$D$9,MATCH(D4,Policy!$A$5:$A$9,0))+Policy!$B$21,"Refer to Manager","Reject - High FOIR"))))) -> Approve
A5: APP1004 | B5: Neha Gupta | C5: Jaipur | D5: Personal Loan | E5: 38 | F5: 93000 | G5: 714 | H5: 370000 | I5: 5 | J5: 0 | K5: =INDEX(Policy!$B$13:$B$17,MATCH(G5,Policy!$A$13:$A$17,1)) -> Good | L5: =INDEX(Policy!$B$5:$B$9,MATCH(D5,Policy!$A$5:$A$9,0))+INDEX(Policy!$C$13:$C$17,MATCH(G5,Policy!$A$13:$A$17,1)) -> 0.1225 | M5: =PMT(L5/12,I5*12,-H5) -> 8277.2652 | N5: =(M5+J5)/F5 -> 0.089002852 | O5: =MAX(0,ROUND(PV(L5/12,I5*12,-(INDEX(Policy!$D$5:$D$9,MATCH(D5,Policy!$A$5:$A$9,0))*F5-J5)),-4)) -> 1870000 | P5: =IF(G5<INDEX(Policy!$E$5:$E$9,MATCH(D5,Policy!$A$5:$A$9,0)),"Reject - Low Score",IF(E5+I5>Policy!$B$20,"Reject - Age",IF(I5>INDEX(Policy!$C$5:$C$9,MATCH(D5,Policy!$A$5:$A$9,0)),"Reject - Tenure",IF(N5<=INDEX(Policy!$D$5:$D$9,MATCH(D5,Policy!$A$5:$A$9,0)),"Approve",IF(N5<=INDEX(Policy!$D$5:$D$9,MATCH(D5,Policy!$A$5:$A$9,0))+Policy!$B$21,"Refer to Manager","Reject - High FOIR"))))) -> Reject - Low Score
A6: APP1005 | B6: Nikhil Singh | C6: Pune | D6: Home Loan | E6: 26 | F6: 42000 | G6: 712 | H6: 1280000 | I6: 10 | J6: 0 | K6: =INDEX(Policy!$B$13:$B$17,MATCH(G6,Policy!$A$13:$A$17,1)) -> Good | L6: =INDEX(Policy!$B$5:$B$9,MATCH(D6,Policy!$A$5:$A$9,0))+INDEX(Policy!$C$13:$C$17,MATCH(G6,Policy!$A$13:$A$17,1)) -> 0.095 | M6: =PMT(L6/12,I6*12,-H6) -> 16562.887 | N6: =(M6+J6)/F6 -> 0.39435446 | O6: =MAX(0,ROUND(PV(L6/12,I6*12,-(INDEX(Policy!$D$5:$D$9,MATCH(D6,Policy!$A$5:$A$9,0))*F6-J6)),-4)) -> 1620000 | P6: =IF(G6<INDEX(Policy!$E$5:$E$9,MATCH(D6,Policy!$A$5:$A$9,0)),"Reject - Low Score",IF(E6+I6>Policy!$B$20,"Reject - Age",IF(I6>INDEX(Policy!$C$5:$C$9,MATCH(D6,Policy!$A$5:$A$9,0)),"Reject - Tenure",IF(N6<=INDEX(Policy!$D$5:$D$9,MATCH(D6,Policy!$A$5:$A$9,0)),"Approve",IF(N6<=INDEX(Policy!$D$5:$D$9,MATCH(D6,Policy!$A$5:$A$9,0))+Policy!$B$21,"Refer to Manager","Reject - High FOIR"))))) -> Approve
A7: APP1006 | B7: Karan Khan | C7: Bengaluru | D7: Home Loan | E7: 42 | F7: 74000 | G7: 785 | H7: 2570000 | I7: 20 | J7: 0 | K7: =INDEX(Policy!$B$13:$B$17,MATCH(G7,Policy!$A$13:$A$17,1)) -> Very Good | L7: =INDEX(Policy!$B$5:$B$9,MATCH(D7,Policy!$A$5:$A$9,0))+INDEX(Policy!$C$13:$C$17,MATCH(G7,Policy!$A$13:$A$17,1)) -> 0.09 | M7: =PMT(L7/12,I7*12,-H7) -> 23122.957 | N7: =(M7+J7)/F7 -> 0.31247239 | O7: =MAX(0,ROUND(PV(L7/12,I7*12,-(INDEX(Policy!$D$5:$D$9,MATCH(D7,Policy!$A$5:$A$9,0))*F7-J7)),-4)) -> 4110000 | P7: =IF(G7<INDEX(Policy!$E$5:$E$9,MATCH(D7,Policy!$A$5:$A$9,0)),"Reject - Low Score",IF(E7+I7>Policy!$B$20,"Reject - Age",IF(I7>INDEX(Policy!$C$5:$C$9,MATCH(D7,Policy!$A$5:$A$9,0)),"Reject - Tenure",IF(N7<=INDEX(Policy!$D$5:$D$9,MATCH(D7,Policy!$A$5:$A$9,0)),"Approve",IF(N7<=INDEX(Policy!$D$5:$D$9,MATCH(D7,Policy!$A$5:$A$9,0))+Policy!$B$21,"Refer to Manager","Reject - High FOIR"))))) -> Approve
A8: APP1007 | B8: Nikhil Rao | C8: Bengaluru | D8: Auto Loan | E8: 45 | F8: 44000 | G8: 813 | H8: 370000 | I8: 5 | J8: 9000 | K8: =INDEX(Policy!$B$13:$B$17,MATCH(G8,Policy!$A$13:$A$17,1)) -> Excellent | L8: =INDEX(Policy!$B$5:$B$9,MATCH(D8,Policy!$A$5:$A$9,0))+INDEX(Policy!$C$13:$C$17,MATCH(G8,Policy!$A$13:$A$17,1)) -> 0.0925 | M8: =PMT(L8/12,I8*12,-H8) -> 7725.5624 | N8: =(M8+J8)/F8 -> 0.38012642 | O8: =MAX(0,ROUND(PV(L8/12,I8*12,-(INDEX(Policy!$D$5:$D$9,MATCH(D8,Policy!$A$5:$A$9,0))*F8-J8)),-4)) -> 620000 | P8: =IF(G8<INDEX(Policy!$E$5:$E$9,MATCH(D8,Policy!$A$5:$A$9,0)),"Reject - Low Score",IF(E8+I8>Policy!$B$20,"Reject - Age",IF(I8>INDEX(Policy!$C$5:$C$9,MATCH(D8,Policy!$A$5:$A$9,0)),"Reject - Tenure",IF(N8<=INDEX(Policy!$D$5:$D$9,MATCH(D8,Policy!$A$5:$A$9,0)),"Approve",IF(N8<=INDEX(Policy!$D$5:$D$9,MATCH(D8,Policy!$A$5:$A$9,0))+Policy!$B$21,"Refer to Manager","Reject - High FOIR"))))) -> Approve
A9: APP1008 | B9: Pranav Das | C9: Delhi | D9: Home Loan | E9: 28 | F9: 71000 | G9: 772 | H9: 1480000 | I9: 30 | J9: 18000 | K9: =INDEX(Policy!$B$13:$B$17,MATCH(G9,Policy!$A$13:$A$17,1)) -> Very Good | L9: =INDEX(Policy!$B$5:$B$9,MATCH(D9,Policy!$A$5:$A$9,0))+INDEX(Policy!$C$13:$C$17,MATCH(G9,Policy!$A$13:$A$17,1)) -> 0.09 | M9: =PMT(L9/12,I9*12,-H9) -> 11908.415 | N9: =(M9+J9)/F9 -> 0.42124528 | O9: =MAX(0,ROUND(PV(L9/12,I9*12,-(INDEX(Policy!$D$5:$D$9,MATCH(D9,Policy!$A$5:$A$9,0))*F9-J9)),-4)) -> 2170000 | P9: =IF(G9<INDEX(Policy!$E$5:$E$9,MATCH(D9,Policy!$A$5:$A$9,0)),"Reject - Low Score",IF(E9+I9>Policy!$B$20,"Reject - Age",IF(I9>INDEX(Policy!$C$5:$C$9,MATCH(D9,Policy!$A$5:$A$9,0)),"Reject - Tenure",IF(N9<=INDEX(Policy!$D$5:$D$9,MATCH(D9,Policy!$A$5:$A$9,0)),"Approve",IF(N9<=INDEX(Policy!$D$5:$D$9,MATCH(D9,Policy!$A$5:$A$9,0))+Policy!$B$21,"Refer to Manager","Reject - High FOIR"))))) -> Approve
A10: APP1009 | B10: Pranav Tiwari | C10: Indore | D10: Home Loan | E10: 35 | F10: 67000 | G10: 782 | H10: 2690000 | I10: 30 | J10: 10500 | K10: =INDEX(Policy!$B$13:$B$17,MATCH(G10,Policy!$A$13:$A$17,1)) -> Very Good | L10: =INDEX(Policy!$B$5:$B$9,MATCH(D10,Policy!$A$5:$A$9,0))+INDEX(Policy!$C$13:$C$17,MATCH(G10,Policy!$A$13:$A$17,1)) -> 0.09 | M10: =PMT(L10/12,I10*12,-H10) -> 21644.348 | N10: =(M10+J10)/F10 -> 0.47976639 | O10: =MAX(0,ROUND(PV(L10/12,I10*12,-(INDEX(Policy!$D$5:$D$9,MATCH(D10,Policy!$A$5:$A$9,0))*F10-J10)),-4)) -> 2860000 | P10: =IF(G10<INDEX(Policy!$E$5:$E$9,MATCH(D10,Policy!$A$5:$A$9,0)),"Reject - Low Score",IF(E10+I10>Policy!$B$20,"Reject - Age",IF(I10>INDEX(Policy!$C$5:$C$9,MATCH(D10,Policy!$A$5:$A$9,0)),"Reject - Tenure",IF(N10<=INDEX(Policy!$D$5:$D$9,MATCH(D10,Policy!$A$5:$A$9,0)),"Approve",IF(N10<=INDEX(Policy!$D$5:$D$9,MATCH(D10,Policy!$A$5:$A$9,0))+Policy!$B$21,"Refer to Manager","Reject - High FOIR"))))) -> Approve
A11: APP1010 | B11: Amit Mehta | C11: Bengaluru | D11: Home Loan | E11: 29 | F11: 28000 | G11: 655 | H11: 510000 | I11: 20 | J11: 0 | K11: =INDEX(Policy!$B$13:$B$17,MATCH(G11,Policy!$A$13:$A$17,1)) -> Fair | L11: =INDEX(Policy!$B$5:$B$9,MATCH(D11,Policy!$A$5:$A$9,0))+INDEX(Policy!$C$13:$C$17,MATCH(G11,Policy!$A$13:$A$17,1)) -> 0.1025 | M11: =PMT(L11/12,I11*12,-H11) -> 5006.3813 | N11: =(M11+J11)/F11 -> 0.17879933 | O11: =MAX(0,ROUND(PV(L11/12,I11*12,-(INDEX(Policy!$D$5:$D$9,MATCH(D11,Policy!$A$5:$A$9,0))*F11-J11)),-4)) -> 1430000 | P11: =IF(G11<INDEX(Policy!$E$5:$E$9,MATCH(D11,Policy!$A$5:$A$9,0)),"Reject - Low Score",IF(E11+I11>Policy!$B$20,"Reject - Age",IF(I11>INDEX(Policy!$C$5:$C$9,MATCH(D11,Policy!$A$5:$A$9,0)),"Reject - Tenure",IF(N11<=INDEX(Policy!$D$5:$D$9,MATCH(D11,Policy!$A$5:$A$9,0)),"Approve",IF(N11<=INDEX(Policy!$D$5:$D$9,MATCH(D11,Policy!$A$5:$A$9,0))+Policy!$B$21,"Refer to Manager","Reject - High FOIR"))))) -> Reject - Low Score
A12: APP1011 | B12: Arjun Chauhan | C12: Hyderabad | D12: Personal Loan | E12: 47 | F12: 87000 | G12: 816 | H12: 160000 | I12: 2 | J12: 0 | K12: =INDEX(Policy!$B$13:$B$17,MATCH(G12,Policy!$A$13:$A$17,1)) -> Excellent | L12: =INDEX(Policy!$B$5:$B$9,MATCH(D12,Policy!$A$5:$A$9,0))+INDEX(Policy!$C$13:$C$17,MATCH(G12,Policy!$A$13:$A$17,1)) -> 0.115 | M12: =PMT(L12/12,I12*12,-H12) -> 7494.4504 | N12: =(M12+J12)/F12 -> 0.086143109 | O12: =MAX(0,ROUND(PV(L12/12,I12*12,-(INDEX(Policy!$D$5:$D$9,MATCH(D12,Policy!$A$5:$A$9,0))*F12-J12)),-4)) -> 840000 | P12: =IF(G12<INDEX(Policy!$E$5:$E$9,MATCH(D12,Policy!$A$5:$A$9,0)),"Reject - Low Score",IF(E12+I12>Policy!$B$20,"Reject - Age",IF(I12>INDEX(Policy!$C$5:$C$9,MATCH(D12,Policy!$A$5:$A$9,0)),"Reject - Tenure",IF(N12<=INDEX(Policy!$D$5:$D$9,MATCH(D12,Policy!$A$5:$A$9,0)),"Approve",IF(N12<=INDEX(Policy!$D$5:$D$9,MATCH(D12,Policy!$A$5:$A$9,0))+Policy!$B$21,"Refer to Manager","Reject - High FOIR"))))) -> Approve
A13: APP1012 | B13: Swati Jain | C13: Delhi | D13: Auto Loan | E13: 30 | F13: 67000 | G13: 651 | H13: 540000 | I13: 5 | J13: 4500 | K13: =INDEX(Policy!$B$13:$B$17,MATCH(G13,Policy!$A$13:$A$17,1)) -> Fair | L13: =INDEX(Policy!$B$5:$B$9,MATCH(D13,Policy!$A$5:$A$9,0))+INDEX(Policy!$C$13:$C$17,MATCH(G13,Policy!$A$13:$A$17,1)) -> 0.1075 | M13: =PMT(L13/12,I13*12,-H13) -> 11673.695 | N13: =(M13+J13)/F13 -> 0.24139843 | O13: =MAX(0,ROUND(PV(L13/12,I13*12,-(INDEX(Policy!$D$5:$D$9,MATCH(D13,Policy!$A$5:$A$9,0))*F13-J13)),-4)) -> 1340000 | P13: =IF(G13<INDEX(Policy!$E$5:$E$9,MATCH(D13,Policy!$A$5:$A$9,0)),"Reject - Low Score",IF(E13+I13>Policy!$B$20,"Reject - Age",IF(I13>INDEX(Policy!$C$5:$C$9,MATCH(D13,Policy!$A$5:$A$9,0)),"Reject - Tenure",IF(N13<=INDEX(Policy!$D$5:$D$9,MATCH(D13,Policy!$A$5:$A$9,0)),"Approve",IF(N13<=INDEX(Policy!$D$5:$D$9,MATCH(D13,Policy!$A$5:$A$9,0))+Policy!$B$21,"Refer to Manager","Reject - High FOIR"))))) -> Reject - Low Score
... A121: APP1120 | B121: Harsh Verma | C121: Mumbai | D121: Home Loan | E121: 33 | F121: 135000 | G121: 774 | H121: 3180000 | I121: 20 | J121: 0 | K121: =INDEX(Policy!$B$13:$B$17,MATCH(G121,Policy!$A$13:$A$17,1)) -> Very Good | L121: =INDEX(Policy!$B$5:$B$9,MATCH(D121,Policy!$A$5:$A$9,0))+INDEX(Policy!$C$13:$C$17,MATCH(G121,Policy!$A$13:$A$17,1)) -> 0.09 | M121: =PMT(L121/12,I121*12,-H121) -> 28611.285 | N121: =(M121+J121)/F121 -> 0.21193545 | O121: =MAX(0,ROUND(PV(L121/12,I121*12,-(INDEX(Policy!$D$5:$D$9,MATCH(D121,Policy!$A$5:$A$9,0))*F121-J121)),-4)) -> 7500000 | P121: =IF(G121<INDEX(Policy!$E$5:$E$9,MATCH(D121,Policy!$A$5:$A$9,0)),"Reject - Low Score",IF(E121+I121>Policy!$B$20,"Reject - Age",IF(I121>INDEX(Policy!$C$5:$C$9,MATCH(D121,Policy!$A$5:$A$9,0)),"Reject - Tenure",IF(N121<=INDEX(Policy!$D$5:$D$9,MATCH(D121,Policy!$A$5:$A$9,0)),"Approve",IF(N121<=INDEX(Policy!$D$5:$D$9,MATCH(D121,Policy!$A$5:$A$9,0))+Policy!$B$21,"Refer to Manager","Reject - High FOIR"))))) -> Approve

Sheet Policy
A1: Lending Policy (assumptions)
A2: Illustrative policy used for this project - NOT ICICI Bank's actual rate card or credit policy. Change the blue cells and everything updates.
A4: Product | B4: Base Rate (p.a.) | C4: Max Tenure (yrs) | D4: Max FOIR | E4: Min Credit Score
A5: Home Loan | B5: 0.0875 | C5: 30 | D5: 0.5 | E5: 700
A6: Auto Loan | B6: 0.0925 | C6: 7 | D6: 0.5 | E6: 690
A7: Personal Loan | B7: 0.115 | C7: 5 | D7: 0.45 | E7: 720
A8: Education Loan | B8: 0.095 | C8: 15 | D8: 0.55 | E8: 650
A9: Business Loan | B9: 0.12 | C9: 7 | D9: 0.5 | E9: 700
A12: Min Score | B12: Score Band | C12: Rate Premium
A13: 0 | B13: Poor | C13: 0.025
A14: 650 | B14: Fair | C14: 0.015
A15: 700 | B15: Good | C15: 0.0075
A16: 750 | B16: Very Good | C16: 0.0025
A17: 800 | B17: Excellent | C17: 0
A20: Max age at loan maturity | B20: 65
A21: Refer-to-manager buffer over max FOIR | B21: 0.05
A23: FOIR = (new EMI + existing EMIs) / monthly income. Final rate = base rate of product + premium for the applicant's score band.

Sheet Summary
A1: Summary Tables
A2: Everything here is COUNTIFS / SUMIFS / AVERAGEIFS on the Data sheet, so it refreshes when Data or Policy changes. Amounts in ₹ crore.
A4: 1. Product-wise
A5: Product | B5: Applications | C5: Requested (₹ cr) | D5: Approved | E5: Referred | F5: Rejected | G5: Approval % | H5: Avg Rate | I5: Avg FOIR | J5: Approved Amt (₹ cr)
A6: =Policy!A5 -> Home Loan | B6: =COUNTIF(Data!$D$2:$D$121,A6) -> 38 | C6: =SUMIF(Data!$D$2:$D$121,A6,Data!$H$2:$H$121)/10000000 -> 8.739 | D6: =COUNTIFS(Data!$D$2:$D$121,A6,Data!$P$2:$P$121,"Approve") -> 19 | E6: =COUNTIFS(Data!$D$2:$D$121,A6,Data!$P$2:$P$121,"Refer to Manager") -> 4 | F6: =B6-D6-E6 -> 15 | G6: =IF(B6=0,0,D6/B6) -> 0.5 | H6: =IFERROR(AVERAGEIF(Data!$D$2:$D$121,A6,Data!$L$2:$L$121),0) -> 0.093092105 | I6: =IFERROR(AVERAGEIF(Data!$D$2:$D$121,A6,Data!$N$2:$N$121),0) -> 0.36062086 | J6: =SUMIFS(Data!$H$2:$H$121,Data!$D$2:$D$121,A6,Data!$P$2:$P$121,"Approve")/10000000 -> 4.692
A7: =Policy!A6 -> Auto Loan | B7: =COUNTIF(Data!$D$2:$D$121,A7) -> 27 | C7: =SUMIF(Data!$D$2:$D$121,A7,Data!$H$2:$H$121)/10000000 -> 1.641 | D7: =COUNTIFS(Data!$D$2:$D$121,A7,Data!$P$2:$P$121,"Approve") -> 25 | E7: =COUNTIFS(Data!$D$2:$D$121,A7,Data!$P$2:$P$121,"Refer to Manager") -> 0 | F7: =B7-D7-E7 -> 2 | G7: =IF(B7=0,0,D7/B7) -> 0.92592593 | H7: =IFERROR(AVERAGEIF(Data!$D$2:$D$121,A7,Data!$L$2:$L$121),0) -> 0.097407407 | I7: =IFERROR(AVERAGEIF(Data!$D$2:$D$121,A7,Data!$N$2:$N$121),0) -> 0.26133086 | J7: =SUMIFS(Data!$H$2:$H$121,Data!$D$2:$D$121,A7,Data!$P$2:$P$121,"Approve")/10000000 -> 1.477
A8: =Policy!A7 -> Personal Loan | B8: =COUNTIF(Data!$D$2:$D$121,A8) -> 27 | C8: =SUMIF(Data!$D$2:$D$121,A8,Data!$H$2:$H$121)/10000000 -> 0.816 | D8: =COUNTIFS(Data!$D$2:$D$121,A8,Data!$P$2:$P$121,"Approve") -> 17 | E8: =COUNTIFS(Data!$D$2:$D$121,A8,Data!$P$2:$P$121,"Refer to Manager") -> 0 | F8: =B8-D8-E8 -> 10 | G8: =IF(B8=0,0,D8/B8) -> 0.62962963 | H8: =IFERROR(AVERAGEIF(Data!$D$2:$D$121,A8,Data!$L$2:$L$121),0) -> 0.12185185 | I8: =IFERROR(AVERAGEIF(Data!$D$2:$D$121,A8,Data!$N$2:$N$121),0) -> 0.15900432 | J8: =SUMIFS(Data!$H$2:$H$121,Data!$D$2:$D$121,A8,Data!$P$2:$P$121,"Approve")/10000000 -> 0.527
A9: =Policy!A8 -> Education Loan | B9: =COUNTIF(Data!$D$2:$D$121,A9) -> 13 | C9: =SUMIF(Data!$D$2:$D$121,A9,Data!$H$2:$H$121)/10000000 -> 1.523 | D9: =COUNTIFS(Data!$D$2:$D$121,A9,Data!$P$2:$P$121,"Approve") -> 13 | E9: =COUNTIFS(Data!$D$2:$D$121,A9,Data!$P$2:$P$121,"Refer to Manager") -> 0 | F9: =B9-D9-E9 -> 0 | G9: =IF(B9=0,0,D9/B9) -> 1 | H9: =IFERROR(AVERAGEIF(Data!$D$2:$D$121,A9,Data!$L$2:$L$121),0) -> 0.10288462 | I9: =IFERROR(AVERAGEIF(Data!$D$2:$D$121,A9,Data!$N$2:$N$121),0) -> 0.26717185 | J9: =SUMIFS(Data!$H$2:$H$121,Data!$D$2:$D$121,A9,Data!$P$2:$P$121,"Approve")/10000000 -> 1.523
A10: =Policy!A9 -> Business Loan | B10: =COUNTIF(Data!$D$2:$D$121,A10) -> 15 | C10: =SUMIF(Data!$D$2:$D$121,A10,Data!$H$2:$H$121)/10000000 -> 2.072 | D10: =COUNTIFS(Data!$D$2:$D$121,A10,Data!$P$2:$P$121,"Approve") -> 6 | E10: =COUNTIFS(Data!$D$2:$D$121,A10,Data!$P$2:$P$121,"Refer to Manager") -> 1 | F10: =B10-D10-E10 -> 8 | G10: =IF(B10=0,0,D10/B10) -> 0.4 | H10: =IFERROR(AVERAGEIF(Data!$D$2:$D$121,A10,Data!$L$2:$L$121),0) -> 0.12666667 | I10: =IFERROR(AVERAGEIF(Data!$D$2:$D$121,A10,Data!$N$2:$N$121),0) -> 0.46339269 | J10: =SUMIFS(Data!$H$2:$H$121,Data!$D$2:$D$121,A10,Data!$P$2:$P$121,"Approve")/10000000 -> 1.125
A11: Total | B11: =SUM(B6:B10) -> 120 | C11: =SUM(C6:C10) -> 14.791 | D11: =SUM(D6:D10) -> 80 | E11: =SUM(E6:E10) -> 5 | F11: =SUM(F6:F10) -> 35 | G11: =IF(B11=0,0,D11/B11) -> 0.66666667 | H11: =AVERAGE(Data!$L$2:$L$121) -> 0.10579167 | I11: =AVERAGE(Data!$N$2:$N$121) -> 0.29563973 | J11: =SUM(J6:J10) -> 9.344
A14: 2. Decision breakdown
A15: Decision | B15: Count | C15: % of total
A16: Approve | B16: =COUNTIF(Data!$P$2:$P$121,A16) -> 80 | C16: =B16/$B$22 -> 0.66666667
A17: Refer to Manager | B17: =COUNTIF(Data!$P$2:$P$121,A17) -> 5 | C17: =B17/$B$22 -> 0.041666667
A18: Reject - Low Score | B18: =COUNTIF(Data!$P$2:$P$121,A18) -> 20 | C18: =B18/$B$22 -> 0.16666667
A19: Reject - Age | B19: =COUNTIF(Data!$P$2:$P$121,A19) -> 5 | C19: =B19/$B$22 -> 0.041666667
A20: Reject - Tenure | B20: =COUNTIF(Data!$P$2:$P$121,A20) -> 0 | C20: =B20/$B$22 -> 0
A21: Reject - High FOIR | B21: =COUNTIF(Data!$P$2:$P$121,A21) -> 10 | C21: =B21/$B$22 -> 0.083333333
A22: Total | B22: =SUM(B16:B21) -> 120 | C22: =SUM(C16:C21) -> 1 | D22: =IF(B22=COUNTA(Data!$A$2:$A$121),"ties to Data","CHECK - count mismatch") -> ties to Data
A25: 3. Credit score band (risk-based pricing check)
A26: Score Band | B26: Applications | C26: Approved | D26: Approval % | E26: Avg Rate
A27: =Policy!B13 -> Poor | B27: =COUNTIF(Data!$K$2:$K$121,A27) -> 1 | C27: =COUNTIFS(Data!$K$2:$K$121,A27,Data!$P$2:$P$121,"Approve") -> 0 | D27: =IF(B27=0,0,C27/B27) -> 0 | E27: =IFERROR(AVERAGEIF(Data!$K$2:$K$121,A27,Data!$L$2:$L$121),0) -> 0.1125
A28: =Policy!B14 -> Fair | B28: =COUNTIF(Data!$K$2:$K$121,A28) -> 19 | C28: =COUNTIFS(Data!$K$2:$K$121,A28,Data!$P$2:$P$121,"Approve") -> 5 | D28: =IF(B28=0,0,C28/B28) -> 0.26315789 | E28: =IFERROR(AVERAGEIF(Data!$K$2:$K$121,A28,Data!$L$2:$L$121),0) -> 0.11723684
A29: =Policy!B15 -> Good | B29: =COUNTIF(Data!$K$2:$K$121,A29) -> 42 | C29: =COUNTIFS(Data!$K$2:$K$121,A29,Data!$P$2:$P$121,"Approve") -> 30 | D29: =IF(B29=0,0,C29/B29) -> 0.71428571 | E29: =IFERROR(AVERAGEIF(Data!$K$2:$K$121,A29,Data!$L$2:$L$121),0) -> 0.10928571
A30: =Policy!B16 -> Very Good | B30: =COUNTIF(Data!$K$2:$K$121,A30) -> 43 | C30: =COUNTIFS(Data!$K$2:$K$121,A30,Data!$P$2:$P$121,"Approve") -> 34 | D30: =IF(B30=0,0,C30/B30) -> 0.79069767 | E30: =IFERROR(AVERAGEIF(Data!$K$2:$K$121,A30,Data!$L$2:$L$121),0) -> 0.09994186
A31: =Policy!B17 -> Excellent | B31: =COUNTIF(Data!$K$2:$K$121,A31) -> 15 | C31: =COUNTIFS(Data!$K$2:$K$121,A31,Data!$P$2:$P$121,"Approve") -> 11 | D31: =IF(B31=0,0,C31/B31) -> 0.73333333 | E31: =IFERROR(AVERAGEIF(Data!$K$2:$K$121,A31,Data!$L$2:$L$121),0) -> 0.097833333
A34: 4. City-wise
A35: City | B35: Applications | C35: Requested (₹ cr) | D35: Approved | E35: Approval %
A36: Mumbai | B36: =COUNTIF(Data!$C$2:$C$121,A36) -> 23 | C36: =SUMIF(Data!$C$2:$C$121,A36,Data!$H$2:$H$121)/10000000 -> 3.327 | D36: =COUNTIFS(Data!$C$2:$C$121,A36,Data!$P$2:$P$121,"Approve") -> 15 | E36: =IF(B36=0,0,D36/B36) -> 0.65217391
A37: Delhi | B37: =COUNTIF(Data!$C$2:$C$121,A37) -> 11 | C37: =SUMIF(Data!$C$2:$C$121,A37,Data!$H$2:$H$121)/10000000 -> 1.601 | D37: =COUNTIFS(Data!$C$2:$C$121,A37,Data!$P$2:$P$121,"Approve") -> 5 | E37: =IF(B37=0,0,D37/B37) -> 0.45454545
A38: Bengaluru | B38: =COUNTIF(Data!$C$2:$C$121,A38) -> 24 | C38: =SUMIF(Data!$C$2:$C$121,A38,Data!$H$2:$H$121)/10000000 -> 2.532 | D38: =COUNTIFS(Data!$C$2:$C$121,A38,Data!$P$2:$P$121,"Approve") -> 17 | E38: =IF(B38=0,0,D38/B38) -> 0.70833333
A39: Hyderabad | B39: =COUNTIF(Data!$C$2:$C$121,A39) -> 13 | C39: =SUMIF(Data!$C$2:$C$121,A39,Data!$H$2:$H$121)/10000000 -> 1.337 | D39: =COUNTIFS(Data!$C$2:$C$121,A39,Data!$P$2:$P$121,"Approve") -> 10 | E39: =IF(B39=0,0,D39/B39) -> 0.76923077
A40: Pune | B40: =COUNTIF(Data!$C$2:$C$121,A40) -> 10 | C40: =SUMIF(Data!$C$2:$C$121,A40,Data!$H$2:$H$121)/10000000 -> 0.714 | D40: =COUNTIFS(Data!$C$2:$C$121,A40,Data!$P$2:$P$121,"Approve") -> 10 | E40: =IF(B40=0,0,D40/B40) -> 1
A41: Chennai | B41: =COUNTIF(Data!$C$2:$C$121,A41) -> 3 | C41: =SUMIF(Data!$C$2:$C$121,A41,Data!$H$2:$H$121)/10000000 -> 0.338 | D41: =COUNTIFS(Data!$C$2:$C$121,A41,Data!$P$2:$P$121,"Approve") -> 1 | E41: =IF(B41=0,0,D41/B41) -> 0.33333333
A42: Kolkata | B42: =COUNTIF(Data!$C$2:$C$121,A42) -> 5 | C42: =SUMIF(Data!$C$2:$C$121,A42,Data!$H$2:$H$121)/10000000 -> 0.428 | D42: =COUNTIFS(Data!$C$2:$C$121,A42,Data!$P$2:$P$121,"Approve") -> 3 | E42: =IF(B42=0,0,D42/B42) -> 0.6
A43: Bhopal | B43: =COUNTIF(Data!$C$2:$C$121,A43) -> 9 | C43: =SUMIF(Data!$C$2:$C$121,A43,Data!$H$2:$H$121)/10000000 -> 1.642 | D43: =COUNTIFS(Data!$C$2:$C$121,A43,Data!$P$2:$P$121,"Approve") -> 5 | E43: =IF(B43=0,0,D43/B43) -> 0.55555556
A44: Indore | B44: =COUNTIF(Data!$C$2:$C$121,A44) -> 12 | C44: =SUMIF(Data!$C$2:$C$121,A44,Data!$H$2:$H$121)/10000000 -> 2.022 | D44: =COUNTIFS(Data!$C$2:$C$121,A44,Data!$P$2:$P$121,"Approve") -> 8 | E44: =IF(B44=0,0,D44/B44) -> 0.66666667
A45: Jaipur | B45: =COUNTIF(Data!$C$2:$C$121,A45) -> 10 | C45: =SUMIF(Data!$C$2:$C$121,A45,Data!$H$2:$H$121)/10000000 -> 0.85 | D45: =COUNTIFS(Data!$C$2:$C$121,A45,Data!$P$2:$P$121,"Approve") -> 6 | E45: =IF(B45=0,0,D45/B45) -> 0.6

Sheet EMI_Calculator
A1: EMI Calculator + Amortisation Schedule
A2: Pick a product and fill the yellow cells. Rate comes from the Policy sheet (base rate + score-band premium).
A4: Product | B4: Home Loan | D4: Interest rate (p.a.) | E4: =INDEX(Policy!$B$5:$B$9,MATCH(B4,Policy!$A$5:$A$9,0))+INDEX(Policy!$C$13:$C$17,MATCH(B7,Policy!$A$13:$A$17,1)) -> 0.095
A5: Loan amount (₹) | B5: 5000000 | D5: Monthly EMI (₹) | E5: =PMT(E4/12,B6*12,-B5) -> 46606.559
A6: Tenure (years) | B6: 20 | D6: Total interest (₹) | E6: =E5*B6*12-B5 -> 6185574.3
A7: Credit score | B7: 745 | D7: Total payment (₹) | E7: =E5*B6*12 -> 11185574
D8: Interest as % of loan | E8: =E6/B5 -> 1.2371149
D9: Tenure allowed by policy? | E9: =IF(B6<=INDEX(Policy!$C$5:$C$9,MATCH(B4,Policy!$A$5:$A$9,0)),"Yes","No - exceeds max tenure") -> Yes
A11: Yearly view
A12: Year | B12: Principal paid (₹) | C12: Interest paid (₹) | D12: Closing balance (₹) | G12: Month | H12: Year | I12: Opening Bal (₹) | J12: EMI (₹) | K12: Interest (₹) | L12: Principal (₹) | M12: Closing Bal (₹)
A13: =IF(1<=$B$6,1,"") -> 1 | B13: =IF(A13="","",SUMIF($H$13:$H$372,A13,$L$13:$L$372)) -> 88046.933 | C13: =IF(A13="","",SUMIF($H$13:$H$372,A13,$K$13:$K$372)) -> 471231.78 | D13: =IF(A13="","",INDEX($M$13:$M$372,A13*12)) -> 4911953.1 | G13: =IF(1<=$B$6*12,1,"") -> 1 | H13: =IF(G13="","",ROUNDUP(G13/12,0)) -> 1 | I13: =IF(G13="","",$B$5) -> 5000000 | J13: =IF(G13="","",$E$5) -> 46606.559 | K13: =IF(G13="","",I13*$E$4/12) -> 39583.333 | L13: =IF(G13="","",J13-K13) -> 7023.2261 | M13: =IF(G13="","",MAX(0,I13-L13)) -> 4992976.8
A14: =IF(2<=$B$6,2,"") -> 2 | B14: =IF(A14="","",SUMIF($H$13:$H$372,A14,$L$13:$L$372)) -> 96785.378 | C14: =IF(A14="","",SUMIF($H$13:$H$372,A14,$K$13:$K$372)) -> 462493.33 | D14: =IF(A14="","",INDEX($M$13:$M$372,A14*12)) -> 4815167.7 | G14: =IF(2<=$B$6*12,2,"") -> 2 | H14: =IF(G14="","",ROUNDUP(G14/12,0)) -> 1 | I14: =IF(G14="","",M13) -> 4992976.8 | J14: =IF(G14="","",$E$5) -> 46606.559 | K14: =IF(G14="","",I14*$E$4/12) -> 39527.733 | L14: =IF(G14="","",J14-K14) -> 7078.8266 | M14: =IF(G14="","",MAX(0,I14-L14)) -> 4985897.9
A15: =IF(3<=$B$6,3,"") -> 3 | B15: =IF(A15="","",SUMIF($H$13:$H$372,A15,$L$13:$L$372)) -> 106391.09 | C15: =IF(A15="","",SUMIF($H$13:$H$372,A15,$K$13:$K$372)) -> 452887.62 | D15: =IF(A15="","",INDEX($M$13:$M$372,A15*12)) -> 4708776.6 | G15: =IF(3<=$B$6*12,3,"") -> 3 | H15: =IF(G15="","",ROUNDUP(G15/12,0)) -> 1 | I15: =IF(G15="","",M14) -> 4985897.9 | J15: =IF(G15="","",$E$5) -> 46606.559 | K15: =IF(G15="","",I15*$E$4/12) -> 39471.692 | L15: =IF(G15="","",J15-K15) -> 7134.8673 | M15: =IF(G15="","",MAX(0,I15-L15)) -> 4978763.1
A16: =IF(4<=$B$6,4,"") -> 4 | B16: =IF(A16="","",SUMIF($H$13:$H$372,A16,$L$13:$L$372)) -> 116950.15 | C16: =IF(A16="","",SUMIF($H$13:$H$372,A16,$K$13:$K$372)) -> 442328.56 | D16: =IF(A16="","",INDEX($M$13:$M$372,A16*12)) -> 4591826.4 | G16: =IF(4<=$B$6*12,4,"") -> 4 | H16: =IF(G16="","",ROUNDUP(G16/12,0)) -> 1 | I16: =IF(G16="","",M15) -> 4978763.1 | J16: =IF(G16="","",$E$5) -> 46606.559 | K16: =IF(G16="","",I16*$E$4/12) -> 39415.208 | L16: =IF(G16="","",J16-K16) -> 7191.3517 | M16: =IF(G16="","",MAX(0,I16-L16)) -> 4971571.7
A17: =IF(5<=$B$6,5,"") -> 5 | B17: =IF(A17="","",SUMIF($H$13:$H$372,A17,$L$13:$L$372)) -> 128557.17 | C17: =IF(A17="","",SUMIF($H$13:$H$372,A17,$K$13:$K$372)) -> 430721.54 | D17: =IF(A17="","",INDEX($M$13:$M$372,A17*12)) -> 4463269.3 | G17: =IF(5<=$B$6*12,5,"") -> 5 | H17: =IF(G17="","",ROUNDUP(G17/12,0)) -> 1 | I17: =IF(G17="","",M16) -> 4971571.7 | J17: =IF(G17="","",$E$5) -> 46606.559 | K17: =IF(G17="","",I17*$E$4/12) -> 39358.276 | L17: =IF(G17="","",J17-K17) -> 7248.2832 | M17: =IF(G17="","",MAX(0,I17-L17)) -> 4964323.4
A18: =IF(6<=$B$6,6,"") -> 6 | B18: =IF(A18="","",SUMIF($H$13:$H$372,A18,$L$13:$L$372)) -> 141316.16 | C18: =IF(A18="","",SUMIF($H$13:$H$372,A18,$K$13:$K$372)) -> 417962.55 | D18: =IF(A18="","",INDEX($M$13:$M$372,A18*12)) -> 4321953.1 | G18: =IF(6<=$B$6*12,6,"") -> 6 | H18: =IF(G18="","",ROUNDUP(G18/12,0)) -> 1 | I18: =IF(G18="","",M17) -> 4964323.4 | J18: =IF(G18="","",$E$5) -> 46606.559 | K18: =IF(G18="","",I18*$E$4/12) -> 39300.894 | L18: =IF(G18="","",J18-K18) -> 7305.6655 | M18: =IF(G18="","",MAX(0,I18-L18)) -> 4957017.8
A19: =IF(7<=$B$6,7,"") -> 7 | B19: =IF(A19="","",SUMIF($H$13:$H$372,A19,$L$13:$L$372)) -> 155341.45 | C19: =IF(A19="","",SUMIF($H$13:$H$372,A19,$K$13:$K$372)) -> 403937.26 | D19: =IF(A19="","",INDEX($M$13:$M$372,A19*12)) -> 4166611.7 | G19: =IF(7<=$B$6*12,7,"") -> 7 | H19: =IF(G19="","",ROUNDUP(G19/12,0)) -> 1 | I19: =IF(G19="","",M18) -> 4957017.8 | J19: =IF(G19="","",$E$5) -> 46606.559 | K19: =IF(G19="","",I19*$E$4/12) -> 39243.057 | L19: =IF(G19="","",J19-K19) -> 7363.502 | M19: =IF(G19="","",MAX(0,I19-L19)) -> 4949654.3
A20: =IF(8<=$B$6,8,"") -> 8 | B20: =IF(A20="","",SUMIF($H$13:$H$372,A20,$L$13:$L$372)) -> 170758.71 | C20: =IF(A20="","",SUMIF($H$13:$H$372,A20,$K$13:$K$372)) -> 388520 | D20: =IF(A20="","",INDEX($M$13:$M$372,A20*12)) -> 3995852.9 | G20: =IF(8<=$B$6*12,8,"") -> 8 | H20: =IF(G20="","",ROUNDUP(G20/12,0)) -> 1 | I20: =IF(G20="","",M19) -> 4949654.3 | J20: =IF(G20="","",$E$5) -> 46606.559 | K20: =IF(G20="","",I20*$E$4/12) -> 39184.763 | L20: =IF(G20="","",J20-K20) -> 7421.7964 | M20: =IF(G20="","",MAX(0,I20-L20)) -> 4942232.5
A21: =IF(9<=$B$6,9,"") -> 9 | B21: =IF(A21="","",SUMIF($H$13:$H$372,A21,$L$13:$L$372)) -> 187706.1 | C21: =IF(A21="","",SUMIF($H$13:$H$372,A21,$K$13:$K$372)) -> 371572.61 | D21: =IF(A21="","",INDEX($M$13:$M$372,A21*12)) -> 3808146.8 | G21: =IF(9<=$B$6*12,9,"") -> 9 | H21: =IF(G21="","",ROUNDUP(G21/12,0)) -> 1 | I21: =IF(G21="","",M20) -> 4942232.5 | J21: =IF(G21="","",$E$5) -> 46606.559 | K21: =IF(G21="","",I21*$E$4/12) -> 39126.007 | L21: =IF(G21="","",J21-K21) -> 7480.5522 | M21: =IF(G21="","",MAX(0,I21-L21)) -> 4934751.9
A22: =IF(10<=$B$6,10,"") -> 10 | B22: =IF(A22="","",SUMIF($H$13:$H$372,A22,$L$13:$L$372)) -> 206335.48 | C22: =IF(A22="","",SUMIF($H$13:$H$372,A22,$K$13:$K$372)) -> 352943.23 | D22: =IF(A22="","",INDEX($M$13:$M$372,A22*12)) -> 3601811.4 | G22: =IF(10<=$B$6*12,10,"") -> 10 | H22: =IF(G22="","",ROUNDUP(G22/12,0)) -> 1 | I22: =IF(G22="","",M21) -> 4934751.9 | J22: =IF(G22="","",$E$5) -> 46606.559 | K22: =IF(G22="","",I22*$E$4/12) -> 39066.786 | L22: =IF(G22="","",J22-K22) -> 7539.7733 | M22: =IF(G22="","",MAX(0,I22-L22)) -> 4927212.2
A23: =IF(11<=$B$6,11,"") -> 11 | B23: =IF(A23="","",SUMIF($H$13:$H$372,A23,$L$13:$L$372)) -> 226813.78 | C23: =IF(A23="","",SUMIF($H$13:$H$372,A23,$K$13:$K$372)) -> 332464.94 | D23: =IF(A23="","",INDEX($M$13:$M$372,A23*12)) -> 3374997.6 | G23: =IF(11<=$B$6*12,11,"") -> 11 | H23: =IF(G23="","",ROUNDUP(G23/12,0)) -> 1 | I23: =IF(G23="","",M22) -> 4927212.2 | J23: =IF(G23="","",$E$5) -> 46606.559 | K23: =IF(G23="","",I23*$E$4/12) -> 39007.096 | L23: =IF(G23="","",J23-K23) -> 7599.4632 | M23: =IF(G23="","",MAX(0,I23-L23)) -> 4919612.7
A24: =IF(12<=$B$6,12,"") -> 12 | B24: =IF(A24="","",SUMIF($H$13:$H$372,A24,$L$13:$L$372)) -> 249324.5 | C24: =IF(A24="","",SUMIF($H$13:$H$372,A24,$K$13:$K$372)) -> 309954.22 | D24: =IF(A24="","",INDEX($M$13:$M$372,A24*12)) -> 3125673.1 | G24: =IF(12<=$B$6*12,12,"") -> 12 | H24: =IF(G24="","",ROUNDUP(G24/12,0)) -> 1 | I24: =IF(G24="","",M23) -> 4919612.7 | J24: =IF(G24="","",$E$5) -> 46606.559 | K24: =IF(G24="","",I24*$E$4/12) -> 38946.934 | L24: =IF(G24="","",J24-K24) -> 7659.6256 | M24: =IF(G24="","",MAX(0,I24-L24)) -> 4911953.1
A25: =IF(13<=$B$6,13,"") -> 13 | B25: =IF(A25="","",SUMIF($H$13:$H$372,A25,$L$13:$L$372)) -> 274069.35 | C25: =IF(A25="","",SUMIF($H$13:$H$372,A25,$K$13:$K$372)) -> 285209.36 | D25: =IF(A25="","",INDEX($M$13:$M$372,A25*12)) -> 2851603.7 | G25: =IF(13<=$B$6*12,13,"") -> 13 | H25: =IF(G25="","",ROUNDUP(G25/12,0)) -> 2 | I25: =IF(G25="","",M24) -> 4911953.1 | J25: =IF(G25="","",$E$5) -> 46606.559 | K25: =IF(G25="","",I25*$E$4/12) -> 38886.295 | L25: =IF(G25="","",J25-K25) -> 7720.2643 | M25: =IF(G25="","",MAX(0,I25-L25)) -> 4904232.8
A26: =IF(14<=$B$6,14,"") -> 14 | B26: =IF(A26="","",SUMIF($H$13:$H$372,A26,$L$13:$L$372)) -> 301270.07 | C26: =IF(A26="","",SUMIF($H$13:$H$372,A26,$K$13:$K$372)) -> 258008.64 | D26: =IF(A26="","",INDEX($M$13:$M$372,A26*12)) -> 2550333.7 | G26: =IF(14<=$B$6*12,14,"") -> 14 | H26: =IF(G26="","",ROUNDUP(G26/12,0)) -> 2 | I26: =IF(G26="","",M25) -> 4904232.8 | J26: =IF(G26="","",$E$5) -> 46606.559 | K26: =IF(G26="","",I26*$E$4/12) -> 38825.176 | L26: =IF(G26="","",J26-K26) -> 7781.383 | M26: =IF(G26="","",MAX(0,I26-L26)) -> 4896451.4
A27: =IF(15<=$B$6,15,"") -> 15 | B27: =IF(A27="","",SUMIF($H$13:$H$372,A27,$L$13:$L$372)) -> 331170.4 | C27: =IF(A27="","",SUMIF($H$13:$H$372,A27,$K$13:$K$372)) -> 228108.32 | D27: =IF(A27="","",INDEX($M$13:$M$372,A27*12)) -> 2219163.3 | G27: =IF(15<=$B$6*12,15,"") -> 15 | H27: =IF(G27="","",ROUNDUP(G27/12,0)) -> 2 | I27: =IF(G27="","",M26) -> 4896451.4 | J27: =IF(G27="","",$E$5) -> 46606.559 | K27: =IF(G27="","",I27*$E$4/12) -> 38763.574 | L27: =IF(G27="","",J27-K27) -> 7842.9857 | M27: =IF(G27="","",MAX(0,I27-L27)) -> 4888608.4
A28: =IF(16<=$B$6,16,"") -> 16 | B28: =IF(A28="","",SUMIF($H$13:$H$372,A28,$L$13:$L$372)) -> 364038.26 | C28: =IF(A28="","",SUMIF($H$13:$H$372,A28,$K$13:$K$372)) -> 195240.45 | D28: =IF(A28="","",INDEX($M$13:$M$372,A28*12)) -> 1855125 | G28: =IF(16<=$B$6*12,16,"") -> 16 | H28: =IF(G28="","",ROUNDUP(G28/12,0)) -> 2 | I28: =IF(G28="","",M27) -> 4888608.4 | J28: =IF(G28="","",$E$5) -> 46606.559 | K28: =IF(G28="","",I28*$E$4/12) -> 38701.483 | L28: =IF(G28="","",J28-K28) -> 7905.076 | M28: =IF(G28="","",MAX(0,I28-L28)) -> 4880703.4
A29: =IF(17<=$B$6,17,"") -> 17 | B29: =IF(A29="","",SUMIF($H$13:$H$372,A29,$L$13:$L$372)) -> 400168.18 | C29: =IF(A29="","",SUMIF($H$13:$H$372,A29,$K$13:$K$372)) -> 159110.54 | D29: =IF(A29="","",INDEX($M$13:$M$372,A29*12)) -> 1454956.8 | G29: =IF(17<=$B$6*12,17,"") -> 17 | H29: =IF(G29="","",ROUNDUP(G29/12,0)) -> 2 | I29: =IF(G29="","",M28) -> 4880703.4 | J29: =IF(G29="","",$E$5) -> 46606.559 | K29: =IF(G29="","",I29*$E$4/12) -> 38638.902 | L29: =IF(G29="","",J29-K29) -> 7967.6578 | M29: =IF(G29="","",MAX(0,I29-L29)) -> 4872735.7
A30: =IF(18<=$B$6,18,"") -> 18 | B30: =IF(A30="","",SUMIF($H$13:$H$372,A30,$L$13:$L$372)) -> 439883.9 | C30: =IF(A30="","",SUMIF($H$13:$H$372,A30,$K$13:$K$372)) -> 119394.81 | D30: =IF(A30="","",INDEX($M$13:$M$372,A30*12)) -> 1015072.9 | G30: =IF(18<=$B$6*12,18,"") -> 18 | H30: =IF(G30="","",ROUNDUP(G30/12,0)) -> 2 | I30: =IF(G30="","",M29) -> 4872735.7 | J30: =IF(G30="","",$E$5) -> 46606.559 | K30: =IF(G30="","",I30*$E$4/12) -> 38575.824 | L30: =IF(G30="","",J30-K30) -> 8030.7351 | M30: =IF(G30="","",MAX(0,I30-L30)) -> 4864705
A31: =IF(19<=$B$6,19,"") -> 19 | B31: =IF(A31="","",SUMIF($H$13:$H$372,A31,$L$13:$L$372)) -> 483541.32 | C31: =IF(A31="","",SUMIF($H$13:$H$372,A31,$K$13:$K$372)) -> 75737.396 | D31: =IF(A31="","",INDEX($M$13:$M$372,A31*12)) -> 531531.62 | G31: =IF(19<=$B$6*12,19,"") -> 19 | H31: =IF(G31="","",ROUNDUP(G31/12,0)) -> 2 | I31: =IF(G31="","",M30) -> 4864705 | J31: =IF(G31="","",$E$5) -> 46606.559 | K31: =IF(G31="","",I31*$E$4/12) -> 38512.248 | L31: =IF(G31="","",J31-K31) -> 8094.3117 | M31: =IF(G31="","",MAX(0,I31-L31)) -> 4856610.7
A32: =IF(20<=$B$6,20,"") -> 20 | B32: =IF(A32="","",SUMIF($H$13:$H$372,A32,$L$13:$L$372)) -> 531531.62 | C32: =IF(A32="","",SUMIF($H$13:$H$372,A32,$K$13:$K$372)) -> 27747.089 | D32: =IF(A32="","",INDEX($M$13:$M$372,A32*12)) -> 1.6734703e-09 | G32: =IF(20<=$B$6*12,20,"") -> 20 | H32: =IF(G32="","",ROUNDUP(G32/12,0)) -> 2 | I32: =IF(G32="","",M31) -> 4856610.7 | J32: =IF(G32="","",$E$5) -> 46606.559 | K32: =IF(G32="","",I32*$E$4/12) -> 38448.168 | L32: =IF(G32="","",J32-K32) -> 8158.3917 | M32: =IF(G32="","",MAX(0,I32-L32)) -> 4848452.3
A33: =IF(21<=$B$6,21,"") | B33: =IF(A33="","",SUMIF($H$13:$H$372,A33,$L$13:$L$372)) | C33: =IF(A33="","",SUMIF($H$13:$H$372,A33,$K$13:$K$372)) | D33: =IF(A33="","",INDEX($M$13:$M$372,A33*12)) | G33: =IF(21<=$B$6*12,21,"") -> 21 | H33: =IF(G33="","",ROUNDUP(G33/12,0)) -> 2 | I33: =IF(G33="","",M32) -> 4848452.3 | J33: =IF(G33="","",$E$5) -> 46606.559 | K33: =IF(G33="","",I33*$E$4/12) -> 38383.58 | L33: =IF(G33="","",J33-K33) -> 8222.979 | M33: =IF(G33="","",MAX(0,I33-L33)) -> 4840229.3
A34: =IF(22<=$B$6,22,"") | B34: =IF(A34="","",SUMIF($H$13:$H$372,A34,$L$13:$L$372)) | C34: =IF(A34="","",SUMIF($H$13:$H$372,A34,$K$13:$K$372)) | D34: =IF(A34="","",INDEX($M$13:$M$372,A34*12)) | G34: =IF(22<=$B$6*12,22,"") -> 22 | H34: =IF(G34="","",ROUNDUP(G34/12,0)) -> 2 | I34: =IF(G34="","",M33) -> 4840229.3 | J34: =IF(G34="","",$E$5) -> 46606.559 | K34: =IF(G34="","",I34*$E$4/12) -> 38318.482 | L34: =IF(G34="","",J34-K34) -> 8288.0776 | M34: =IF(G34="","",MAX(0,I34-L34)) -> 4831941.2
A35: =IF(23<=$B$6,23,"") | B35: =IF(A35="","",SUMIF($H$13:$H$372,A35,$L$13:$L$372)) | C35: =IF(A35="","",SUMIF($H$13:$H$372,A35,$K$13:$K$372)) | D35: =IF(A35="","",INDEX($M$13:$M$372,A35*12)) | G35: =IF(23<=$B$6*12,23,"") -> 23 | H35: =IF(G35="","",ROUNDUP(G35/12,0)) -> 2 | I35: =IF(G35="","",M34) -> 4831941.2 | J35: =IF(G35="","",$E$5) -> 46606.559 | K35: =IF(G35="","",I35*$E$4/12) -> 38252.868 | L35: =IF(G35="","",J35-K35) -> 8353.6915 | M35: =IF(G35="","",MAX(0,I35-L35)) -> 4823587.5
A36: =IF(24<=$B$6,24,"") | B36: =IF(A36="","",SUMIF($H$13:$H$372,A36,$L$13:$L$372)) | C36: =IF(A36="","",SUMIF($H$13:$H$372,A36,$K$13:$K$372)) | D36: =IF(A36="","",INDEX($M$13:$M$372,A36*12)) | G36: =IF(24<=$B$6*12,24,"") -> 24 | H36: =IF(G36="","",ROUNDUP(G36/12,0)) -> 2 | I36: =IF(G36="","",M35) -> 4823587.5 | J36: =IF(G36="","",$E$5) -> 46606.559 | K36: =IF(G36="","",I36*$E$4/12) -> 38186.734 | L36: =IF(G36="","",J36-K36) -> 8419.8249 | M36: =IF(G36="","",MAX(0,I36-L36)) -> 4815167.7
A37: =IF(25<=$B$6,25,"") | B37: =IF(A37="","",SUMIF($H$13:$H$372,A37,$L$13:$L$372)) | C37: =IF(A37="","",SUMIF($H$13:$H$372,A37,$K$13:$K$372)) | D37: =IF(A37="","",INDEX($M$13:$M$372,A37*12)) | G37: =IF(25<=$B$6*12,25,"") -> 25 | H37: =IF(G37="","",ROUNDUP(G37/12,0)) -> 3 | I37: =IF(G37="","",M36) -> 4815167.7 | J37: =IF(G37="","",$E$5) -> 46606.559 | K37: =IF(G37="","",I37*$E$4/12) -> 38120.078 | L37: =IF(G37="","",J37-K37) -> 8486.4819 | M37: =IF(G37="","",MAX(0,I37-L37)) -> 4806681.2
A38: =IF(26<=$B$6,26,"") | B38: =IF(A38="","",SUMIF($H$13:$H$372,A38,$L$13:$L$372)) | C38: =IF(A38="","",SUMIF($H$13:$H$372,A38,$K$13:$K$372)) | D38: =IF(A38="","",INDEX($M$13:$M$372,A38*12)) | G38: =IF(26<=$B$6*12,26,"") -> 26 | H38: =IF(G38="","",ROUNDUP(G38/12,0)) -> 3 | I38: =IF(G38="","",M37) -> 4806681.2 | J38: =IF(G38="","",$E$5) -> 46606.559 | K38: =IF(G38="","",I38*$E$4/12) -> 38052.893 | L38: =IF(G38="","",J38-K38) -> 8553.6665 | M38: =IF(G38="","",MAX(0,I38-L38)) -> 4798127.5
A39: =IF(27<=$B$6,27,"") | B39: =IF(A39="","",SUMIF($H$13:$H$372,A39,$L$13:$L$372)) | C39: =IF(A39="","",SUMIF($H$13:$H$372,A39,$K$13:$K$372)) | D39: =IF(A39="","",INDEX($M$13:$M$372,A39*12)) | G39: =IF(27<=$B$6*12,27,"") -> 27 | H39: =IF(G39="","",ROUNDUP(G39/12,0)) -> 3 | I39: =IF(G39="","",M38) -> 4798127.5 | J39: =IF(G39="","",$E$5) -> 46606.559 | K39: =IF(G39="","",I39*$E$4/12) -> 37985.176 | L39: =IF(G39="","",J39-K39) -> 8621.383 | M39: =IF(G39="","",MAX(0,I39-L39)) -> 4789506.2
A40: =IF(28<=$B$6,28,"") | B40: =IF(A40="","",SUMIF($H$13:$H$372,A40,$L$13:$L$372)) | C40: =IF(A40="","",SUMIF($H$13:$H$372,A40,$K$13:$K$372)) | D40: =IF(A40="","",INDEX($M$13:$M$372,A40*12)) | G40: =IF(28<=$B$6*12,28,"") -> 28 | H40: =IF(G40="","",ROUNDUP(G40/12,0)) -> 3 | I40: =IF(G40="","",M39) -> 4789506.2 | J40: =IF(G40="","",$E$5) -> 46606.559 | K40: =IF(G40="","",I40*$E$4/12) -> 37916.924 | L40: =IF(G40="","",J40-K40) -> 8689.6356 | M40: =IF(G40="","",MAX(0,I40-L40)) -> 4780816.5
A41: =IF(29<=$B$6,29,"") | B41: =IF(A41="","",SUMIF($H$13:$H$372,A41,$L$13:$L$372)) | C41: =IF(A41="","",SUMIF($H$13:$H$372,A41,$K$13:$K$372)) | D41: =IF(A41="","",INDEX($M$13:$M$372,A41*12)) | G41: =IF(29<=$B$6*12,29,"") -> 29 | H41: =IF(G41="","",ROUNDUP(G41/12,0)) -> 3 | I41: =IF(G41="","",M40) -> 4780816.5 | J41: =IF(G41="","",$E$5) -> 46606.559 | K41: =IF(G41="","",I41*$E$4/12) -> 37848.131 | L41: =IF(G41="","",J41-K41) -> 8758.4286 | M41: =IF(G41="","",MAX(0,I41-L41)) -> 4772058.1
A42: =IF(30<=$B$6,30,"") | B42: =IF(A42="","",SUMIF($H$13:$H$372,A42,$L$13:$L$372)) | C42: =IF(A42="","",SUMIF($H$13:$H$372,A42,$K$13:$K$372)) | D42: =IF(A42="","",INDEX($M$13:$M$372,A42*12)) | G42: =IF(30<=$B$6*12,30,"") -> 30 | H42: =IF(G42="","",ROUNDUP(G42/12,0)) -> 3 | I42: =IF(G42="","",M41) -> 4772058.1 | J42: =IF(G42="","",$E$5) -> 46606.559 | K42: =IF(G42="","",I42*$E$4/12) -> 37778.793 | L42: =IF(G42="","",J42-K42) -> 8827.7662 | M42: =IF(G42="","",MAX(0,I42-L42)) -> 4763230.3
G43: =IF(31<=$B$6*12,31,"") -> 31 | H43: =IF(G43="","",ROUNDUP(G43/12,0)) -> 3 | I43: =IF(G43="","",M42) -> 4763230.3 | J43: =IF(G43="","",$E$5) -> 46606.559 | K43: =IF(G43="","",I43*$E$4/12) -> 37708.907 | L43: =IF(G43="","",J43-K43) -> 8897.6526 | M43: =IF(G43="","",MAX(0,I43-L43)) -> 4754332.7
A44: Check: principal repaid = loan amount | D44: =ROUND(SUM(B13:B42)-B5,0) -> 0 | G44: =IF(32<=$B$6*12,32,"") -> 32 | H44: =IF(G44="","",ROUNDUP(G44/12,0)) -> 3 | I44: =IF(G44="","",M43) -> 4754332.7 | J44: =IF(G44="","",$E$5) -> 46606.559 | K44: =IF(G44="","",I44*$E$4/12) -> 37638.467 | L44: =IF(G44="","",J44-K44) -> 8968.0924 | M44: =IF(G44="","",MAX(0,I44-L44)) -> 4745364.6
G45: =IF(33<=$B$6*12,33,"") -> 33 | H45: =IF(G45="","",ROUNDUP(G45/12,0)) -> 3 | I45: =IF(G45="","",M44) -> 4745364.6 | J45: =IF(G45="","",$E$5) -> 46606.559 | K45: =IF(G45="","",I45*$E$4/12) -> 37567.47 | L45: =IF(G45="","",J45-K45) -> 9039.0898 | M45: =IF(G45="","",MAX(0,I45-L45)) -> 4736325.5
G46: =IF(34<=$B$6*12,34,"") -> 34 | H46: =IF(G46="","",ROUNDUP(G46/12,0)) -> 3 | I46: =IF(G46="","",M45) -> 4736325.5 | J46: =IF(G46="","",$E$5) -> 46606.559 | K46: =IF(G46="","",I46*$E$4/12) -> 37495.91 | L46: =IF(G46="","",J46-K46) -> 9110.6492 | M46: =IF(G46="","",MAX(0,I46-L46)) -> 4727214.8
G47: =IF(35<=$B$6*12,35,"") -> 35 | H47: =IF(G47="","",ROUNDUP(G47/12,0)) -> 3 | I47: =IF(G47="","",M46) -> 4727214.8 | J47: =IF(G47="","",$E$5) -> 46606.559 | K47: =IF(G47="","",I47*$E$4/12) -> 37423.784 | L47: =IF(G47="","",J47-K47) -> 9182.7752 | M47: =IF(G47="","",MAX(0,I47-L47)) -> 4718032.1
G48: =IF(36<=$B$6*12,36,"") -> 36 | H48: =IF(G48="","",ROUNDUP(G48/12,0)) -> 3 | I48: =IF(G48="","",M47) -> 4718032.1 | J48: =IF(G48="","",$E$5) -> 46606.559 | K48: =IF(G48="","",I48*$E$4/12) -> 37351.087 | L48: =IF(G48="","",J48-K48) -> 9255.4722 | M48: =IF(G48="","",MAX(0,I48-L48)) -> 4708776.6
G49: =IF(37<=$B$6*12,37,"") -> 37 | H49: =IF(G49="","",ROUNDUP(G49/12,0)) -> 4 | I49: =IF(G49="","",M48) -> 4708776.6 | J49: =IF(G49="","",$E$5) -> 46606.559 | K49: =IF(G49="","",I49*$E$4/12) -> 37277.815 | L49: =IF(G49="","",J49-K49) -> 9328.7447 | M49: =IF(G49="","",MAX(0,I49-L49)) -> 4699447.9
G50: =IF(38<=$B$6*12,38,"") -> 38 | H50: =IF(G50="","",ROUNDUP(G50/12,0)) -> 4 | I50: =IF(G50="","",M49) -> 4699447.9 | J50: =IF(G50="","",$E$5) -> 46606.559 | K50: =IF(G50="","",I50*$E$4/12) -> 37203.962 | L50: =IF(G50="","",J50-K50) -> 9402.5972 | M50: =IF(G50="","",MAX(0,I50-L50)) -> 4690045.3
G51: =IF(39<=$B$6*12,39,"") -> 39 | H51: =IF(G51="","",ROUNDUP(G51/12,0)) -> 4 | I51: =IF(G51="","",M50) -> 4690045.3 | J51: =IF(G51="","",$E$5) -> 46606.559 | K51: =IF(G51="","",I51*$E$4/12) -> 37129.525 | L51: =IF(G51="","",J51-K51) -> 9477.0345 | M51: =IF(G51="","",MAX(0,I51-L51)) -> 4680568.2
G52: =IF(40<=$B$6*12,40,"") -> 40 | H52: =IF(G52="","",ROUNDUP(G52/12,0)) -> 4 | I52: =IF(G52="","",M51) -> 4680568.2 | J52: =IF(G52="","",$E$5) -> 46606.559 | K52: =IF(G52="","",I52*$E$4/12) -> 37054.498 | L52: =IF(G52="","",J52-K52) -> 9552.061 | M52: =IF(G52="","",MAX(0,I52-L52)) -> 4671016.2
G53: =IF(41<=$B$6*12,41,"") -> 41 | H53: =IF(G53="","",ROUNDUP(G53/12,0)) -> 4 | I53: =IF(G53="","",M52) -> 4671016.2 | J53: =IF(G53="","",$E$5) -> 46606.559 | K53: =IF(G53="","",I53*$E$4/12) -> 36978.878 | L53: =IF(G53="","",J53-K53) -> 9627.6815 | M53: =IF(G53="","",MAX(0,I53-L53)) -> 4661388.5
G54: =IF(42<=$B$6*12,42,"") -> 42 | H54: =IF(G54="","",ROUNDUP(G54/12,0)) -> 4 | I54: =IF(G54="","",M53) -> 4661388.5 | J54: =IF(G54="","",$E$5) -> 46606.559 | K54: =IF(G54="","",I54*$E$4/12) -> 36902.659 | L54: =IF(G54="","",J54-K54) -> 9703.9006 | M54: =IF(G54="","",MAX(0,I54-L54)) -> 4651684.6
G55: =IF(43<=$B$6*12,43,"") -> 43 | H55: =IF(G55="","",ROUNDUP(G55/12,0)) -> 4 | I55: =IF(G55="","",M54) -> 4651684.6 | J55: =IF(G55="","",$E$5) -> 46606.559 | K55: =IF(G55="","",I55*$E$4/12) -> 36825.836 | L55: =IF(G55="","",J55-K55) -> 9780.7232 | M55: =IF(G55="","",MAX(0,I55-L55)) -> 4641903.9
G56: =IF(44<=$B$6*12,44,"") -> 44 | H56: =IF(G56="","",ROUNDUP(G56/12,0)) -> 4 | I56: =IF(G56="","",M55) -> 4641903.9 | J56: =IF(G56="","",$E$5) -> 46606.559 | K56: =IF(G56="","",I56*$E$4/12) -> 36748.406 | L56: =IF(G56="","",J56-K56) -> 9858.1539 | M56: =IF(G56="","",MAX(0,I56-L56)) -> 4632045.7
G57: =IF(45<=$B$6*12,45,"") -> 45 | H57: =IF(G57="","",ROUNDUP(G57/12,0)) -> 4 | I57: =IF(G57="","",M56) -> 4632045.7 | J57: =IF(G57="","",$E$5) -> 46606.559 | K57: =IF(G57="","",I57*$E$4/12) -> 36670.362 | L57: =IF(G57="","",J57-K57) -> 9936.1976 | M57: =IF(G57="","",MAX(0,I57-L57)) -> 4622109.5
G58: =IF(46<=$B$6*12,46,"") -> 46 | H58: =IF(G58="","",ROUNDUP(G58/12,0)) -> 4 | I58: =IF(G58="","",M57) -> 4622109.5 | J58: =IF(G58="","",$E$5) -> 46606.559 | K58: =IF(G58="","",I58*$E$4/12) -> 36591.7 | L58: =IF(G58="","",J58-K58) -> 10014.859 | M58: =IF(G58="","",MAX(0,I58-L58)) -> 4612094.6
G59: =IF(47<=$B$6*12,47,"") -> 47 | H59: =IF(G59="","",ROUNDUP(G59/12,0)) -> 4 | I59: =IF(G59="","",M58) -> 4612094.6 | J59: =IF(G59="","",$E$5) -> 46606.559 | K59: =IF(G59="","",I59*$E$4/12) -> 36512.416 | L59: =IF(G59="","",J59-K59) -> 10094.143 | M59: =IF(G59="","",MAX(0,I59-L59)) -> 4602000.5
G60: =IF(48<=$B$6*12,48,"") -> 48 | H60: =IF(G60="","",ROUNDUP(G60/12,0)) -> 4 | I60: =IF(G60="","",M59) -> 4602000.5 | J60: =IF(G60="","",$E$5) -> 46606.559 | K60: =IF(G60="","",I60*$E$4/12) -> 36432.504 | L60: =IF(G60="","",J60-K60) -> 10174.055 | M60: =IF(G60="","",MAX(0,I60-L60)) -> 4591826.4
G61: =IF(49<=$B$6*12,49,"") -> 49 | H61: =IF(G61="","",ROUNDUP(G61/12,0)) -> 5 | I61: =IF(G61="","",M60) -> 4591826.4 | J61: =IF(G61="","",$E$5) -> 46606.559 | K61: =IF(G61="","",I61*$E$4/12) -> 36351.959 | L61: =IF(G61="","",J61-K61) -> 10254.6 | M61: =IF(G61="","",MAX(0,I61-L61)) -> 4581571.8
G62: =IF(50<=$B$6*12,50,"") -> 50 | H62: =IF(G62="","",ROUNDUP(G62/12,0)) -> 5 | I62: =IF(G62="","",M61) -> 4581571.8 | J62: =IF(G62="","",$E$5) -> 46606.559 | K62: =IF(G62="","",I62*$E$4/12) -> 36270.777 | L62: =IF(G62="","",J62-K62) -> 10335.782 | M62: =IF(G62="","",MAX(0,I62-L62)) -> 4571236.1
G63: =IF(51<=$B$6*12,51,"") -> 51 | H63: =IF(G63="","",ROUNDUP(G63/12,0)) -> 5 | I63: =IF(G63="","",M62) -> 4571236.1 | J63: =IF(G63="","",$E$5) -> 46606.559 | K63: =IF(G63="","",I63*$E$4/12) -> 36188.952 | L63: =IF(G63="","",J63-K63) -> 10417.607 | M63: =IF(G63="","",MAX(0,I63-L63)) -> 4560818.5
G64: =IF(52<=$B$6*12,52,"") -> 52 | H64: =IF(G64="","",ROUNDUP(G64/12,0)) -> 5 | I64: =IF(G64="","",M63) -> 4560818.5 | J64: =IF(G64="","",$E$5) -> 46606.559 | K64: =IF(G64="","",I64*$E$4/12) -> 36106.479 | L64: =IF(G64="","",J64-K64) -> 10500.08 | M64: =IF(G64="","",MAX(0,I64-L64)) -> 4550318.4
G65: =IF(53<=$B$6*12,53,"") -> 53 | H65: =IF(G65="","",ROUNDUP(G65/12,0)) -> 5 | I65: =IF(G65="","",M64) -> 4550318.4 | J65: =IF(G65="","",$E$5) -> 46606.559 | K65: =IF(G65="","",I65*$E$4/12) -> 36023.354 | L65: =IF(G65="","",J65-K65) -> 10583.206 | M65: =IF(G65="","",MAX(0,I65-L65)) -> 4539735.2
G66: =IF(54<=$B$6*12,54,"") -> 54 | H66: =IF(G66="","",ROUNDUP(G66/12,0)) -> 5 | I66: =IF(G66="","",M65) -> 4539735.2 | J66: =IF(G66="","",$E$5) -> 46606.559 | K66: =IF(G66="","",I66*$E$4/12) -> 35939.57 | L66: =IF(G66="","",J66-K66) -> 10666.989 | M66: =IF(G66="","",MAX(0,I66-L66)) -> 4529068.2
G67: =IF(55<=$B$6*12,55,"") -> 55 | H67: =IF(G67="","",ROUNDUP(G67/12,0)) -> 5 | I67: =IF(G67="","",M66) -> 4529068.2 | J67: =IF(G67="","",$E$5) -> 46606.559 | K67: =IF(G67="","",I67*$E$4/12) -> 35855.123 | L67: =IF(G67="","",J67-K67) -> 10751.436 | M67: =IF(G67="","",MAX(0,I67-L67)) -> 4518316.7
G68: =IF(56<=$B$6*12,56,"") -> 56 | H68: =IF(G68="","",ROUNDUP(G68/12,0)) -> 5 | I68: =IF(G68="","",M67) -> 4518316.7 | J68: =IF(G68="","",$E$5) -> 46606.559 | K68: =IF(G68="","",I68*$E$4/12) -> 35770.008 | L68: =IF(G68="","",J68-K68) -> 10836.552 | M68: =IF(G68="","",MAX(0,I68-L68)) -> 4507480.2
G69: =IF(57<=$B$6*12,57,"") -> 57 | H69: =IF(G69="","",ROUNDUP(G69/12,0)) -> 5 | I69: =IF(G69="","",M68) -> 4507480.2 | J69: =IF(G69="","",$E$5) -> 46606.559 | K69: =IF(G69="","",I69*$E$4/12) -> 35684.218 | L69: =IF(G69="","",J69-K69) -> 10922.341 | M69: =IF(G69="","",MAX(0,I69-L69)) -> 4496557.8
G70: =IF(58<=$B$6*12,58,"") -> 58 | H70: =IF(G70="","",ROUNDUP(G70/12,0)) -> 5 | I70: =IF(G70="","",M69) -> 4496557.8 | J70: =IF(G70="","",$E$5) -> 46606.559 | K70: =IF(G70="","",I70*$E$4/12) -> 35597.75 | L70: =IF(G70="","",J70-K70) -> 11008.81 | M70: =IF(G70="","",MAX(0,I70-L70)) -> 4485549
G71: =IF(59<=$B$6*12,59,"") -> 59 | H71: =IF(G71="","",ROUNDUP(G71/12,0)) -> 5 | I71: =IF(G71="","",M70) -> 4485549 | J71: =IF(G71="","",$E$5) -> 46606.559 | K71: =IF(G71="","",I71*$E$4/12) -> 35510.597 | L71: =IF(G71="","",J71-K71) -> 11095.963 | M71: =IF(G71="","",MAX(0,I71-L71)) -> 4474453.1
G72: =IF(60<=$B$6*12,60,"") -> 60 | H72: =IF(G72="","",ROUNDUP(G72/12,0)) -> 5 | I72: =IF(G72="","",M71) -> 4474453.1 | J72: =IF(G72="","",$E$5) -> 46606.559 | K72: =IF(G72="","",I72*$E$4/12) -> 35422.754 | L72: =IF(G72="","",J72-K72) -> 11183.806 | M72: =IF(G72="","",MAX(0,I72-L72)) -> 4463269.3
G73: =IF(61<=$B$6*12,61,"") -> 61 | H73: =IF(G73="","",ROUNDUP(G73/12,0)) -> 6 | I73: =IF(G73="","",M72) -> 4463269.3 | J73: =IF(G73="","",$E$5) -> 46606.559 | K73: =IF(G73="","",I73*$E$4/12) -> 35334.215 | L73: =IF(G73="","",J73-K73) -> 11272.344 | M73: =IF(G73="","",MAX(0,I73-L73)) -> 4451996.9
G74: =IF(62<=$B$6*12,62,"") -> 62 | H74: =IF(G74="","",ROUNDUP(G74/12,0)) -> 6 | I74: =IF(G74="","",M73) -> 4451996.9 | J74: =IF(G74="","",$E$5) -> 46606.559 | K74: =IF(G74="","",I74*$E$4/12) -> 35244.976 | L74: =IF(G74="","",J74-K74) -> 11361.584 | M74: =IF(G74="","",MAX(0,I74-L74)) -> 4440635.3
G75: =IF(63<=$B$6*12,63,"") -> 63 | H75: =IF(G75="","",ROUNDUP(G75/12,0)) -> 6 | I75: =IF(G75="","",M74) -> 4440635.3 | J75: =IF(G75="","",$E$5) -> 46606.559 | K75: =IF(G75="","",I75*$E$4/12) -> 35155.03 | L75: =IF(G75="","",J75-K75) -> 11451.53 | M75: =IF(G75="","",MAX(0,I75-L75)) -> 4429183.8
G76: =IF(64<=$B$6*12,64,"") -> 64 | H76: =IF(G76="","",ROUNDUP(G76/12,0)) -> 6 | I76: =IF(G76="","",M75) -> 4429183.8 | J76: =IF(G76="","",$E$5) -> 46606.559 | K76: =IF(G76="","",I76*$E$4/12) -> 35064.372 | L76: =IF(G76="","",J76-K76) -> 11542.188 | M76: =IF(G76="","",MAX(0,I76-L76)) -> 4417641.6
G77: =IF(65<=$B$6*12,65,"") -> 65 | H77: =IF(G77="","",ROUNDUP(G77/12,0)) -> 6 | I77: =IF(G77="","",M76) -> 4417641.6 | J77: =IF(G77="","",$E$5) -> 46606.559 | K77: =IF(G77="","",I77*$E$4/12) -> 34972.996 | L77: =IF(G77="","",J77-K77) -> 11633.563 | M77: =IF(G77="","",MAX(0,I77-L77)) -> 4406008.1
G78: =IF(66<=$B$6*12,66,"") -> 66 | H78: =IF(G78="","",ROUNDUP(G78/12,0)) -> 6 | I78: =IF(G78="","",M77) -> 4406008.1 | J78: =IF(G78="","",$E$5) -> 46606.559 | K78: =IF(G78="","",I78*$E$4/12) -> 34880.897 | L78: =IF(G78="","",J78-K78) -> 11725.662 | M78: =IF(G78="","",MAX(0,I78-L78)) -> 4394282.4
G79: =IF(67<=$B$6*12,67,"") -> 67 | H79: =IF(G79="","",ROUNDUP(G79/12,0)) -> 6 | I79: =IF(G79="","",M78) -> 4394282.4 | J79: =IF(G79="","",$E$5) -> 46606.559 | K79: =IF(G79="","",I79*$E$4/12) -> 34788.069 | L79: =IF(G79="","",J79-K79) -> 11818.49 | M79: =IF(G79="","",MAX(0,I79-L79)) -> 4382463.9
G80: =IF(68<=$B$6*12,68,"") -> 68 | H80: =IF(G80="","",ROUNDUP(G80/12,0)) -> 6 | I80: =IF(G80="","",M79) -> 4382463.9 | J80: =IF(G80="","",$E$5) -> 46606.559 | K80: =IF(G80="","",I80*$E$4/12) -> 34694.506 | L80: =IF(G80="","",J80-K80) -> 11912.053 | M80: =IF(G80="","",MAX(0,I80-L80)) -> 4370551.9
G81: =IF(69<=$B$6*12,69,"") -> 69 | H81: =IF(G81="","",ROUNDUP(G81/12,0)) -> 6 | I81: =IF(G81="","",M80) -> 4370551.9 | J81: =IF(G81="","",$E$5) -> 46606.559 | K81: =IF(G81="","",I81*$E$4/12) -> 34600.202 | L81: =IF(G81="","",J81-K81) -> 12006.357 | M81: =IF(G81="","",MAX(0,I81-L81)) -> 4358545.5
G82: =IF(70<=$B$6*12,70,"") -> 70 | H82: =IF(G82="","",ROUNDUP(G82/12,0)) -> 6 | I82: =IF(G82="","",M81) -> 4358545.5 | J82: =IF(G82="","",$E$5) -> 46606.559 | K82: =IF(G82="","",I82*$E$4/12) -> 34505.152 | L82: =IF(G82="","",J82-K82) -> 12101.408 | M82: =IF(G82="","",MAX(0,I82-L82)) -> 4346444.1
G83: =IF(71<=$B$6*12,71,"") -> 71 | H83: =IF(G83="","",ROUNDUP(G83/12,0)) -> 6 | I83: =IF(G83="","",M82) -> 4346444.1 | J83: =IF(G83="","",$E$5) -> 46606.559 | K83: =IF(G83="","",I83*$E$4/12) -> 34409.349 | L83: =IF(G83="","",J83-K83) -> 12197.21 | M83: =IF(G83="","",MAX(0,I83-L83)) -> 4334246.9
G84: =IF(72<=$B$6*12,72,"") -> 72 | H84: =IF(G84="","",ROUNDUP(G84/12,0)) -> 6 | I84: =IF(G84="","",M83) -> 4334246.9 | J84: =IF(G84="","",$E$5) -> 46606.559 | K84: =IF(G84="","",I84*$E$4/12) -> 34312.788 | L84: =IF(G84="","",J84-K84) -> 12293.772 | M84: =IF(G84="","",MAX(0,I84-L84)) -> 4321953.1
G85: =IF(73<=$B$6*12,73,"") -> 73 | H85: =IF(G85="","",ROUNDUP(G85/12,0)) -> 7 | I85: =IF(G85="","",M84) -> 4321953.1 | J85: =IF(G85="","",$E$5) -> 46606.559 | K85: =IF(G85="","",I85*$E$4/12) -> 34215.462 | L85: =IF(G85="","",J85-K85) -> 12391.097 | M85: =IF(G85="","",MAX(0,I85-L85)) -> 4309562
G86: =IF(74<=$B$6*12,74,"") -> 74 | H86: =IF(G86="","",ROUNDUP(G86/12,0)) -> 7 | I86: =IF(G86="","",M85) -> 4309562 | J86: =IF(G86="","",$E$5) -> 46606.559 | K86: =IF(G86="","",I86*$E$4/12) -> 34117.366 | L86: =IF(G86="","",J86-K86) -> 12489.193 | M86: =IF(G86="","",MAX(0,I86-L86)) -> 4297072.8
G87: =IF(75<=$B$6*12,75,"") -> 75 | H87: =IF(G87="","",ROUNDUP(G87/12,0)) -> 7 | I87: =IF(G87="","",M86) -> 4297072.8 | J87: =IF(G87="","",$E$5) -> 46606.559 | K87: =IF(G87="","",I87*$E$4/12) -> 34018.493 | L87: =IF(G87="","",J87-K87) -> 12588.066 | M87: =IF(G87="","",MAX(0,I87-L87)) -> 4284484.8
G88: =IF(76<=$B$6*12,76,"") -> 76 | H88: =IF(G88="","",ROUNDUP(G88/12,0)) -> 7 | I88: =IF(G88="","",M87) -> 4284484.8 | J88: =IF(G88="","",$E$5) -> 46606.559 | K88: =IF(G88="","",I88*$E$4/12) -> 33918.838 | L88: =IF(G88="","",J88-K88) -> 12687.722 | M88: =IF(G88="","",MAX(0,I88-L88)) -> 4271797
G89: =IF(77<=$B$6*12,77,"") -> 77 | H89: =IF(G89="","",ROUNDUP(G89/12,0)) -> 7 | I89: =IF(G89="","",M88) -> 4271797 | J89: =IF(G89="","",$E$5) -> 46606.559 | K89: =IF(G89="","",I89*$E$4/12) -> 33818.393 | L89: =IF(G89="","",J89-K89) -> 12788.166 | M89: =IF(G89="","",MAX(0,I89-L89)) -> 4259008.9
G90: =IF(78<=$B$6*12,78,"") -> 78 | H90: =IF(G90="","",ROUNDUP(G90/12,0)) -> 7 | I90: =IF(G90="","",M89) -> 4259008.9 | J90: =IF(G90="","",$E$5) -> 46606.559 | K90: =IF(G90="","",I90*$E$4/12) -> 33717.154 | L90: =IF(G90="","",J90-K90) -> 12889.406 | M90: =IF(G90="","",MAX(0,I90-L90)) -> 4246119.5
G91: =IF(79<=$B$6*12,79,"") -> 79 | H91: =IF(G91="","",ROUNDUP(G91/12,0)) -> 7 | I91: =IF(G91="","",M90) -> 4246119.5 | J91: =IF(G91="","",$E$5) -> 46606.559 | K91: =IF(G91="","",I91*$E$4/12) -> 33615.112 | L91: =IF(G91="","",J91-K91) -> 12991.447 | M91: =IF(G91="","",MAX(0,I91-L91)) -> 4233128
G92: =IF(80<=$B$6*12,80,"") -> 80 | H92: =IF(G92="","",ROUNDUP(G92/12,0)) -> 7 | I92: =IF(G92="","",M91) -> 4233128 | J92: =IF(G92="","",$E$5) -> 46606.559 | K92: =IF(G92="","",I92*$E$4/12) -> 33512.263 | L92: =IF(G92="","",J92-K92) -> 13094.296 | M92: =IF(G92="","",MAX(0,I92-L92)) -> 4220033.7
G93: =IF(81<=$B$6*12,81,"") -> 81 | H93: =IF(G93="","",ROUNDUP(G93/12,0)) -> 7 | I93: =IF(G93="","",M92) -> 4220033.7 | J93: =IF(G93="","",$E$5) -> 46606.559 | K93: =IF(G93="","",I93*$E$4/12) -> 33408.6 | L93: =IF(G93="","",J93-K93) -> 13197.959 | M93: =IF(G93="","",MAX(0,I93-L93)) -> 4206835.8
G94: =IF(82<=$B$6*12,82,"") -> 82 | H94: =IF(G94="","",ROUNDUP(G94/12,0)) -> 7 | I94: =IF(G94="","",M93) -> 4206835.8 | J94: =IF(G94="","",$E$5) -> 46606.559 | K94: =IF(G94="","",I94*$E$4/12) -> 33304.116 | L94: =IF(G94="","",J94-K94) -> 13302.443 | M94: =IF(G94="","",MAX(0,I94-L94)) -> 4193533.3
G95: =IF(83<=$B$6*12,83,"") -> 83 | H95: =IF(G95="","",ROUNDUP(G95/12,0)) -> 7 | I95: =IF(G95="","",M94) -> 4193533.3 | J95: =IF(G95="","",$E$5) -> 46606.559 | K95: =IF(G95="","",I95*$E$4/12) -> 33198.805 | L95: =IF(G95="","",J95-K95) -> 13407.754 | M95: =IF(G95="","",MAX(0,I95-L95)) -> 4180125.6
G96: =IF(84<=$B$6*12,84,"") -> 84 | H96: =IF(G96="","",ROUNDUP(G96/12,0)) -> 7 | I96: =IF(G96="","",M95) -> 4180125.6 | J96: =IF(G96="","",$E$5) -> 46606.559 | K96: =IF(G96="","",I96*$E$4/12) -> 33092.661 | L96: =IF(G96="","",J96-K96) -> 13513.899 | M96: =IF(G96="","",MAX(0,I96-L96)) -> 4166611.7
G97: =IF(85<=$B$6*12,85,"") -> 85 | H97: =IF(G97="","",ROUNDUP(G97/12,0)) -> 8 | I97: =IF(G97="","",M96) -> 4166611.7 | J97: =IF(G97="","",$E$5) -> 46606.559 | K97: =IF(G97="","",I97*$E$4/12) -> 32985.676 | L97: =IF(G97="","",J97-K97) -> 13620.884 | M97: =IF(G97="","",MAX(0,I97-L97)) -> 4152990.8
G98: =IF(86<=$B$6*12,86,"") -> 86 | H98: =IF(G98="","",ROUNDUP(G98/12,0)) -> 8 | I98: =IF(G98="","",M97) -> 4152990.8 | J98: =IF(G98="","",$E$5) -> 46606.559 | K98: =IF(G98="","",I98*$E$4/12) -> 32877.844 | L98: =IF(G98="","",J98-K98) -> 13728.716 | M98: =IF(G98="","",MAX(0,I98-L98)) -> 4139262.1
G99: =IF(87<=$B$6*12,87,"") -> 87 | H99: =IF(G99="","",ROUNDUP(G99/12,0)) -> 8 | I99: =IF(G99="","",M98) -> 4139262.1 | J99: =IF(G99="","",$E$5) -> 46606.559 | K99: =IF(G99="","",I99*$E$4/12) -> 32769.158 | L99: =IF(G99="","",J99-K99) -> 13837.401 | M99: =IF(G99="","",MAX(0,I99-L99)) -> 4125424.7
G100: =IF(88<=$B$6*12,88,"") -> 88 | H100: =IF(G100="","",ROUNDUP(G100/12,0)) -> 8 | I100: =IF(G100="","",M99) -> 4125424.7 | J100: =IF(G100="","",$E$5) -> 46606.559 | K100: =IF(G100="","",I100*$E$4/12) -> 32659.612 | L100: =IF(G100="","",J100-K100) -> 13946.947 | M100: =IF(G100="","",MAX(0,I100-L100)) -> 4111477.7
G101: =IF(89<=$B$6*12,89,"") -> 89 | H101: =IF(G101="","",ROUNDUP(G101/12,0)) -> 8 | I101: =IF(G101="","",M100) -> 4111477.7 | J101: =IF(G101="","",$E$5) -> 46606.559 | K101: =IF(G101="","",I101*$E$4/12) -> 32549.199 | L101: =IF(G101="","",J101-K101) -> 14057.361 | M101: =IF(G101="","",MAX(0,I101-L101)) -> 4097420.4
G102: =IF(90<=$B$6*12,90,"") -> 90 | H102: =IF(G102="","",ROUNDUP(G102/12,0)) -> 8 | I102: =IF(G102="","",M101) -> 4097420.4 | J102: =IF(G102="","",$E$5) -> 46606.559 | K102: =IF(G102="","",I102*$E$4/12) -> 32437.911 | L102: =IF(G102="","",J102-K102) -> 14168.648 | M102: =IF(G102="","",MAX(0,I102-L102)) -> 4083251.7
...
